boringavatars/__init__.py
boringavatars/bauhaus.py
boringavatars/beam.py
boringavatars/marble.py
boringavatars/pixel.py
boringavatars/py.typed
boringavatars/ring.py
boringavatars/sunset.py
boringavatars/utils.py
boringavatars/templates/bauhaus.svg
boringavatars/templates/beam.svg
boringavatars/templates/marble.svg
boringavatars/templates/pixel.svg
boringavatars/templates/ring.svg
boringavatars/templates/sunset.svg
boringavatars-1.0.3.dist-info/METADATA
boringavatars-1.0.3.dist-info/WHEEL
boringavatars-1.0.3.dist-info/licenses/LICENSE
boringavatars-1.0.3.dist-info/RECORD
