Metadata-Version: 2.1
Name: boringavatars
Version: 1.0.3
Summary: A Python port of the boring-avatars JS library.
Project-URL: Documentation, https://github.com/federicobond/boringavatars
Project-URL: Source, https://github.com/federicobond/boringavatars
Project-URL: Tracker, https://github.com/federicobond/boringavatars
Author-email: Federico Bond <federicobond@gmail.com>
License-File: LICENSE
Classifier: Development Status :: 5 - Production/Stable
Classifier: Intended Audience :: Developers
Classifier: License :: OSI Approved :: MIT License
Classifier: Programming Language :: Python :: 3 :: Only
Classifier: Programming Language :: Python :: 3.8
Classifier: Programming Language :: Python :: 3.9
Classifier: Programming Language :: Python :: 3.10
Classifier: Programming Language :: Python :: 3.11
Requires-Python: >=3.8
Requires-Dist: jinja2>=3.0.0
Provides-Extra: test
Requires-Dist: black==23.12.1; extra == 'test'
Requires-Dist: check-manifest==0.48; extra == 'test'
Requires-Dist: pre-commit==3.5.0; extra == 'test'
